trading_platform/__init__.py
trading_platform/account.py
trading_platform/base.py
trading_platform/client.py
trading_platform/income_statement.py
trading_platform/order.py
trading_platform/position.py
trading_platform/quote.py
trading_platform/quotes.py
trading_platform-0.1.4.dist-info/METADATA
trading_platform-0.1.4.dist-info/WHEEL
trading_platform-0.1.4.dist-info/top_level.txt
trading_platform-0.1.4.dist-info/RECORD
