Metadata-Version: 2.1
Name: trading-platform
Version: 0.1.4
Summary: Trading platform SDK library for Python
Home-page: https://github.com/MihaiBlebea/trading-platform-sdk
Author: Mihai Blebea
Author-email: mihaiserban.blebea@gmail.com
License: MIT
Platform: UNKNOWN
Requires-Dist: requests
